hookup/__init__.py
hookup/hookup.py
hookup-0.1.1.dist-info/WHEEL
hookup-0.1.1.dist-info/METADATA
hookup-0.1.1.dist-info/RECORD
