Metadata-Version: 2.1
Name: hookup
Version: 0.1.1
Summary: Watch attributes on a class and trigger a callback on change
Home-page: https://github.com/shaunrs/python-hookup
License: BSD-3-Clause
Keywords: decorator,decorators,attribute,callback,watch,watcher,hookup,patch
Author: Shaun S
Requires-Python: >=3.7,<4.0
Classifier: Intended Audience :: Developers
Classifier: License :: OSI Approved :: BSD License
Classifier: Programming Language :: Python :: 3
Classifier: Programming Language :: Python :: 3.10
Classifier: Programming Language :: Python :: 3.7
Classifier: Programming Language :: Python :: 3.8
Classifier: Programming Language :: Python :: 3.9
Classifier: Topic :: Software Development
Classifier: Topic :: Software Development :: Libraries :: Python Modules
Classifier: Topic :: Utilities
Project-URL: Repository, https://github.com/shaunrs/python-hookup
